autooptimizer/__init__.py
autooptimizer/cluster.py
autooptimizer/dbscan.py
autooptimizer/decisiontree.py
autooptimizer/ensemble.py
autooptimizer/kmeans.py
autooptimizer/knn.py
autooptimizer/linear_model.py
autooptimizer/logreg.py
autooptimizer/meanshift.py
autooptimizer/metrics.py
autooptimizer/neighbors.py
autooptimizer/outlier.py
autooptimizer/process.py
autooptimizer/svc.py
autooptimizer/svm.py
autooptimizer/tree.py
autooptimizer-0.8.9.dist-info/LICENSE.txt
autooptimizer-0.8.9.dist-info/METADATA
autooptimizer-0.8.9.dist-info/WHEEL
autooptimizer-0.8.9.dist-info/top_level.txt
autooptimizer-0.8.9.dist-info/RECORD
